twtxt_registry_client/__init__.py
twtxt_registry_client/__main__.py
twtxt_registry_client/client.py
twtxt_registry_client/output.py
twtxt_registry_client-0.1.1.dist-info/LICENSE
twtxt_registry_client-0.1.1.dist-info/METADATA
twtxt_registry_client-0.1.1.dist-info/WHEEL
twtxt_registry_client-0.1.1.dist-info/entry_points.txt
twtxt_registry_client-0.1.1.dist-info/top_level.txt
twtxt_registry_client-0.1.1.dist-info/RECORD
